anago/__init__.py
anago/callbacks.py
anago/layers.py
anago/models.py
anago/preprocessing.py
anago/tagger.py
anago/trainer.py
anago/utils.py
anago/wrapper.py
anago_py367-1.0.11.dist-info/LICENSE
anago_py367-1.0.11.dist-info/METADATA
anago_py367-1.0.11.dist-info/WHEEL
anago_py367-1.0.11.dist-info/top_level.txt
anago_py367-1.0.11.dist-info/RECORD
